alpaca_proteomics/__init__.py
alpaca_proteomics/alpaca.py
alpaca_proteomics-0.9.980.dist-info/LICENSE
alpaca_proteomics-0.9.980.dist-info/METADATA
alpaca_proteomics-0.9.980.dist-info/WHEEL
alpaca_proteomics-0.9.980.dist-info/top_level.txt
alpaca_proteomics-0.9.980.dist-info/RECORD
