Metadata-Version: 2.1
Name: alpaca_proteomics
Version: 0.9.980
Summary: Absolute Protein Quantification python library
Author: Borja Ferrero Bordera
Author-email: b.ferrero@med.uni-muenchen.de
License: MIT
Project-URL: Author, https://www.linkedin.com/in/borjaferrero/
License-File: LICENSE
Requires-Dist: matplotlib
Requires-Dist: numpy
Requires-Dist: pandas
Requires-Dist: scikit-learn
Requires-Dist: scipy
Requires-Dist: seaborn
Requires-Dist: XlsxWriter
